exlibris/__init__.py
exlibris/dataset.py
exlibris/stats.py
exlibris/tester.py
exlibris/datasets/Fertility.csv
exlibris/datasets/Hill.csv
exlibris/datasets/ILPD.csv
exlibris/datasets/Liver.csv
exlibris/datasets/Mammo.csv
exlibris/datasets/Musk1.csv
exlibris/datasets/Qsar.csv
exlibris/datasets/Retinopathy.csv
exlibris/datasets/Spam.csv
exlibris/datasets/Spect.csv
exlibris-0.5.0.dist-info/licenses/LICENSE
exlibris-0.5.0.dist-info/METADATA
exlibris-0.5.0.dist-info/WHEEL
exlibris-0.5.0.dist-info/top_level.txt
exlibris-0.5.0.dist-info/RECORD
